skythought/__init__.py
skythought/evals/__init__.py
skythought/evals/cli.py
skythought/evals/inference_and_check.py
skythought/evals/batch/__init__.py
skythought/evals/batch/env_config.py
skythought/evals/batch/pipeline.py
skythought/evals/batch/tokenizer.py
skythought/evals/batch/utils.py
skythought/evals/batch/workload.py
skythought/evals/batch/engines/__init__.py
skythought/evals/batch/engines/base.py
skythought/evals/batch/engines/initializer.py
skythought/evals/batch/engines/vllm_engine.py
skythought/evals/batch/logging/__init__.py
skythought/evals/common/__init__.py
skythought/evals/common/entities.py
skythought/evals/models/__init__.py
skythought/evals/models/base.py
skythought/evals/models/model_configs.yaml
skythought/evals/ray_configs/ray_config.yaml
skythought/evals/tasks/__init__.py
skythought/evals/tasks/base.py
skythought/evals/tasks/task_util.py
skythought/evals/tasks/aime/aime24.yaml
skythought/evals/tasks/aime/aime24_sky.yaml
skythought/evals/tasks/aime/aime25.yaml
skythought/evals/tasks/aime/aime_handler.py
skythought/evals/tasks/amc23/amc23.yaml
skythought/evals/tasks/amc23/amc23_handler.py
skythought/evals/tasks/apps/apps.yaml
skythought/evals/tasks/apps/apps_handler.py
skythought/evals/tasks/apps/apps_util.py
skythought/evals/tasks/arc/arc_c.yaml
skythought/evals/tasks/arc/arc_handler.py
skythought/evals/tasks/gpqa_diamond/gpqa_diamond.yaml
skythought/evals/tasks/gpqa_diamond/gpqa_diamond_handler.py
skythought/evals/tasks/gsm8k/gsm8k.yaml
skythought/evals/tasks/gsm8k/gsm8k_handler.py
skythought/evals/tasks/livecodebench/livecodebench.yaml
skythought/evals/tasks/livecodebench/livecodebench_easy.yaml
skythought/evals/tasks/livecodebench/livecodebench_handler.py
skythought/evals/tasks/livecodebench/livecodebench_hard.yaml
skythought/evals/tasks/livecodebench/livecodebench_medium.yaml
skythought/evals/tasks/livecodebench/livecodebench_util.py
skythought/evals/tasks/math/math500.yaml
skythought/evals/tasks/math/math_handler.py
skythought-0.1.0.dist-info/LICENSE
skythought-0.1.0.dist-info/METADATA
skythought-0.1.0.dist-info/WHEEL
skythought-0.1.0.dist-info/entry_points.txt
skythought-0.1.0.dist-info/top_level.txt
skythought-0.1.0.dist-info/RECORD
