Metadata-Version: 2.2
Name: skythought
Version: 0.1.0
Summary: Skythought Evals: Evaluation and Data Generation Tools for Reasoning Models
Author: NovaSky Team
License: Apache-2.0
Project-URL: Repository, https://github.com/NovaSky-AI/SkyThought
Requires-Python: <3.11,>=3.9
License-File: LICENSE
Requires-Dist: vllm==0.7.0
Requires-Dist: pyext
Requires-Dist: word2number
Requires-Dist: scipy
Requires-Dist: datasets
Requires-Dist: latex2sympy2
Requires-Dist: pydantic
Requires-Dist: setuptools
Requires-Dist: typer
Provides-Extra: dev
Requires-Dist: pytest; extra == "dev"
Requires-Dist: pytest-mock; extra == "dev"
Requires-Dist: black; extra == "dev"
Requires-Dist: ruff; extra == "dev"
Requires-Dist: pre-commit; extra == "dev"
